[
  {
    "id": 91,
    "categories": ["Artificial Intelligence", "Data Science & Analysis"],
    "title": "Fake News Detection System",
    "shortDescription": "AI model using NLP to identify misinformation in digital news articles.",
    "longDescription": "Developed a robust AI solution leveraging Natural Language Processing (NLP) and Passive Aggressive Classifier to distinguish between real and fake news with high accuracy.",
    "icon": "BrainCircuit",
    "gradient": "from-purple-600 to-indigo-700",
    "techStack": ["Python", "Scikit-learn", "TF-IDF", "NLP"],
    "offerings": ["Source Code", "IEEE Paper", "PPT", "Training"],
    "images": ["https://pikwizard.com/pw/medium/15da5bad5a6e007f46a22968e23cf2bc.png", "https://pikwizard.com/pw/medium/e7a67a0f10ef91c22480efea253b5368.png", "https://www.clipartmax.com/png/small/287-2879312_intelligent-solutions-transparent-iot.png", "https://www.clipartmax.com/png/middle/29-298859_internet-of-things.png"]
  }
]
